simple_semantic_search/__init__.py
simple_semantic_search-0.1.0.dist-info/LICENSE.md
simple_semantic_search-0.1.0.dist-info/METADATA
simple_semantic_search-0.1.0.dist-info/WHEEL
simple_semantic_search-0.1.0.dist-info/RECORD
