Metadata-Version: 2.1
Name: simple-semantic-search
Version: 0.1.0
Summary: 
Author: Nathan
Author-email: 11278700+nathansnellaert@users.noreply.github.com
Requires-Python: >=3.11,<4.0
Classifier: Programming Language :: Python :: 3
Classifier: Programming Language :: Python :: 3.11
